README.md
setup.py
pyEmtoCpa/__init__.py
pyEmtoCpa/constant.py
pyEmtoCpa.egg-info/PKG-INFO
pyEmtoCpa.egg-info/SOURCES.txt
pyEmtoCpa.egg-info/dependency_links.txt
pyEmtoCpa.egg-info/not-zip-safe
pyEmtoCpa.egg-info/requires.txt
pyEmtoCpa.egg-info/top_level.txt