Metadata-Version: 2.1
Name: pyEmtoCpa
Version: 0.0.1
Summary: pyEMTO-CPA
Home-page: https://gitee.com/alkemie_gjwang/pyemtocpa
Author: Guanjie Wang
Author-email: gjwang@buaa.edu.cn
License: MIT
Platform: UNKNOWN
